{
	"configurations" : 
	[
		{
			"directories" : 
			[
				{
					"build" : ".",
					"childIndexes" : 
					[
						1
					],
					"hasInstallRule" : true,
					"jsonFile" : "directory-.-Release-9c8fcfdf9d7697d68e13.json",
					"minimumCMakeVersion" : 
					{
						"string" : "3.15"
					},
					"projectIndex" : 0,
					"source" : ".",
					"targetIndexes" : 
					[
						2,
						3,
						4,
						5,
						6
					]
				},
				{
					"build" : "gtest",
					"jsonFile" : "directory-gtest-Release-0908a8c91ddba5d6c989.json",
					"minimumCMakeVersion" : 
					{
						"string" : "3.8"
					},
					"parentIndex" : 0,
					"projectIndex" : 1,
					"source" : "/opt/ros/jazzy/src/gtest_vendor",
					"targetIndexes" : 
					[
						0,
						1
					]
				}
			],
			"name" : "Release",
			"projects" : 
			[
				{
					"childIndexes" : 
					[
						1
					],
					"directoryIndexes" : 
					[
						0
					],
					"name" : "mesh_map",
					"targetIndexes" : 
					[
						2,
						3,
						4,
						5,
						6
					]
				},
				{
					"directoryIndexes" : 
					[
						1
					],
					"name" : "gtest",
					"parentIndex" : 0,
					"targetIndexes" : 
					[
						0,
						1
					]
				}
			],
			"targets" : 
			[
				{
					"directoryIndex" : 1,
					"id" : "gtest::@0af4add9fe94340e763e",
					"jsonFile" : "target-gtest-Release-b889fe84b0b25f049340.json",
					"name" : "gtest",
					"projectIndex" : 1
				},
				{
					"directoryIndex" : 1,
					"id" : "gtest_main::@0af4add9fe94340e763e",
					"jsonFile" : "target-gtest_main-Release-325d85dba447643a889c.json",
					"name" : "gtest_main",
					"projectIndex" : 1
				},
				{
					"directoryIndex" : 0,
					"id" : "mesh_map::@6890427a1f51a3e7e1df",
					"jsonFile" : "target-mesh_map-Release-86d7acc349536e9a839d.json",
					"name" : "mesh_map",
					"projectIndex" : 0
				},
				{
					"directoryIndex" : 0,
					"id" : "mesh_map_mesh_map_test::@6890427a1f51a3e7e1df",
					"jsonFile" : "target-mesh_map_mesh_map_test-Release-9dfc5e7eb48060eb5ffb.json",
					"name" : "mesh_map_mesh_map_test",
					"projectIndex" : 0
				},
				{
					"directoryIndex" : 0,
					"id" : "mesh_map_test_layer_plugin::@6890427a1f51a3e7e1df",
					"jsonFile" : "target-mesh_map_test_layer_plugin-Release-0adddbae9e6e441dd02a.json",
					"name" : "mesh_map_test_layer_plugin",
					"projectIndex" : 0
				},
				{
					"directoryIndex" : 0,
					"id" : "mesh_map_uninstall::@6890427a1f51a3e7e1df",
					"jsonFile" : "target-mesh_map_uninstall-Release-a2b2f5302943c25cd763.json",
					"name" : "mesh_map_uninstall",
					"projectIndex" : 0
				},
				{
					"directoryIndex" : 0,
					"id" : "uninstall::@6890427a1f51a3e7e1df",
					"jsonFile" : "target-uninstall-Release-f745deb4952caa2f4c4a.json",
					"name" : "uninstall",
					"projectIndex" : 0
				}
			]
		}
	],
	"kind" : "codemodel",
	"paths" : 
	{
		"build" : "/root/Shared/MIAPR_Projekt/colcon_ws/build/mesh_map",
		"source" : "/root/Shared/MIAPR_Projekt/colcon_ws/src/mesh_navigation/mesh_map"
	},
	"version" : 
	{
		"major" : 2,
		"minor" : 6
	}
}
